kaleidescape/__init__.py
kaleidescape/connection.py
kaleidescape/const.py
kaleidescape/device.py
kaleidescape/dispatcher.py
kaleidescape/error.py
kaleidescape/message.py
kaleidescape/py.typed
pykaleidescape-2022.2.6.dist-info/LICENSE
pykaleidescape-2022.2.6.dist-info/METADATA
pykaleidescape-2022.2.6.dist-info/WHEEL
pykaleidescape-2022.2.6.dist-info/top_level.txt
pykaleidescape-2022.2.6.dist-info/RECORD
