Metadata-Version: 2.1
Name: pykaleidescape
Version: 2022.2.6
Summary: "A python client library for the Kaleidescape System Control Protocol."
Home-page: https://github.com/SteveEasley/pykaleidescape
Author: Steve Easley
Author-email: tardis74@yahoo.com
License: UNKNOWN
Platform: UNKNOWN
Classifier: Development Status :: 4 - Beta
Classifier: Intended Audience :: Developers
Classifier: License :: OSI Approved :: MIT License
Classifier: Topic :: Home Automation
Classifier: Topic :: Software Development :: Libraries
Classifier: Programming Language :: Python :: 3.9
License-File: LICENSE
Requires-Dist: aiohttp (>=3.8.0)
Requires-Dist: dnspython (>=2.1.0)
